{
  "Menu_Nursing": "Pflege",
  "Menu_Services": "Dienstleister",
  "Menu_Ward": "Station",
  "Menu_Rooms": "Räume",
  "Menu_Patients": "Patienten",
  "Menu_Pharmacy": "Apotheke",
  "Menu_Kitchen": "Küche",
  "Menu_Physio": "Physio",
  "Menu_Beds": "Betten",
  "Menu_DrugStorage": "Medikamentenlager",
  "Menu_Calendar": "Kalender",
  "Menu_Handover": "Übergabe",
  "Menu_Registration": "Registrierung",
  "Menu_Admission": "Aufnahme",
  "Menu_CreatePatient": "Neuer Patient",
  "Menu_PatientList": "Patientenliste",
  "Menu_Admit": "Patient aufnehmen",
  "Menu_OrderDiagnostics": "Tests bestellen",
  "Menu_ScheduleBeds": "Betten planen",
  "Menu_Common": "Allgemein",
  "Menu_Contacts": "Kontaktliste",
  "NewsPage_News": "Nachrichten",
  "NewsPage_General": "Generell",
  "NewsPage_Ward": "Station",
  "NewsPage_MyPatients": "Meine Patienten",
  "Patient_PatientMale": "Patient",
  "Patient_PatientFemale": "Patientin",
  "Patient_BirthdayAbbreviation": "Geb.",
  "Patient_Birtday": "Geburtsdatum",
  "Patient_Tasks": "Aufgaben",
  "Patient_PreexistingConditions": "Vorerkrankungen",
  "Patient_Medication": "Medikamente",
  "Patient_Treatments": "Behandlungen",
  "Patient_TestDiagnostics": "Tests/Diagnostik",
  "Patient_Observations": "Überwachung",
  "Patient_Nursing": "Pflege",
  "Add": "",
  "Birthday": "",
  "Cancel": "",
  "Consumable": "",
  "Consumable_CouldNotLoad": "",
  "Consumable_CouldNotStore": "",
  "Consumable_Name": "",
  "Consumable_Order_CouldNotOrder": "",
  "Consumable_Order_Note": "",
  "Consumable_Order_Quantity": "",
  "Consumable_Order_SuccessfullyOrdered": "",
  "ContactList": "",
  "Contacts_CouldNotLoad": "",
  "Contacts_Email": "",
  "Contacts_Name": "",
  "Contacts_PhoneNumber": "",
  "Department": "",
  "Edit...": "",
  "Employee_CouldNotLoad": "",
  "Employee_CouldNotStore": "",
  "Employee_IDTaken": "",
  "Employee_Stored": "",
  "FirstName": "",
  "ID": "",
  "JanKIS": "",
  "LastName": "",
  "Loading...": "",
  "Next": "",
  "NoEntries": "",
  "Order": "",
  "Ordering...": "",
  "Patient_Birthday": "",
  "Please select...": "",
  "Previous": "",
  "QRCodeModal_PleaseScanQRCodes": "",
  "QRCodeModal_SelectQRCodeType": "",
  "QRCodeModal_Title": "",
  "QRCodeType_Medication": "",
  "QRCodeType_Patient": "",
  "QRCodeType_Resource": "",
  "Resource": "",
  "Resource_Name": "",
  "Role_Name": "",
  "Role_Permissions": "",
  "RoomNumber": "",
  "Save": "",
  "Search": "",
  "Search...": "",
  "Service_Audience": "",
  "Service_Audience_Employee": "",
  "Service_Audience_Patient": "",
  "Service_Audience_RoleName": "",
  "Service_Audience_Type": "",
  "Service_CannotStore": "",
  "Service_CouldNotLoad": "",
  "Service_CreateNew": "",
  "Service_Department": "",
  "Service_Departments_CouldNotLoad": "",
  "Service_Description": "",
  "Service_ID": "",
  "Service_Name": "",
  "Service_Parameter_Description": "",
  "Service_Parameter_Name": "",
  "Service_Parameter_ValueType": "",
  "Service_Parameters": "",
  "Service_Stored": "",
  "ServiceAudienceType_All": "",
  "ServiceAudienceType_Employee": "",
  "ServiceAudienceType_Patient": "",
  "ServiceAudienceType_Role": "",
  "ServiceRequest": "",
  "ServiceRequest_CouldNotSubmit": "",
  "ServiceRequest_Note": "",
  "Services": "",
  "Stock": "",
  "Stock_CouldNotLoad": "",
  "Stock_CouldNotStore": "",
  "Stock_Name": "",
  "Stock_Quantity": "",
  "Stock_SuccessfullyStored": "",
  "StockStatus": "",
  "Store": "",
  "Storing...": "",
  "Submit": "",
  "Submitting...": "",
  "UserManagement": "",
  "UserManagement_CouldNotLoadUsers": "",
  "UserManagement_Roles": "",
  "Department_CouldNotLoad": "",
  "Department_CouldNotStore": "",
  "Department_Employees": "",
  "Department_Name": "",
  "Department_ParentDepartment": "",
  "Department_Services": "",
  "Department_Stocks": "",
  "Department_SuccessfullyStored": "",
  "Departments": "",
  "Departments_CouldNotLoad": "",
  "Diagnostics_CouldNotStore": "",
  "Diagnostics_Description": "",
  "Diagnostics_Name": "",
  "Diagnostics_ScaleType": "",
  "Diagnostics_SuccessfullyStored": "",
  "Diagnostics_TestCodeLocal": "",
  "Diagnostics_TestCodeLoinc": "",
  "Hello": "",
  "LoggingIn...": "",
  "Login": "",
  "Login_CouldNotLogIn": "",
  "LogOut": "",
  "Medication_ActiveIngredient": "",
  "Medication_BrandName": "",
  "Medication_Dosing": "",
  "Medication_Note": "",
  "Menu_Config": "",
  "Menu_Config_Departments": "",
  "Menu_Config_Employees": "",
  "Menu_Config_Institution": "",
  "Menu_Department": "",
  "NotPermitted": "",
  "Password": "",
  "ServiceRequests": "",
  "Services_CouldNotLoad": "",
  "Username": ""
}